hctest/HCtest.py
hctest/__init__.py
higher_criticism_test-0.1.8.dist-info/LICENSE
higher_criticism_test-0.1.8.dist-info/METADATA
higher_criticism_test-0.1.8.dist-info/WHEEL
higher_criticism_test-0.1.8.dist-info/top_level.txt
higher_criticism_test-0.1.8.dist-info/RECORD
